{
    "tokens": [
        {
            "index": 0,
            "isPredicate": false,
            "isModifier": false,
            "label": null,
            "start": 0,
            "end": 0,
            "text": "This",
            "pb": null,
            "vn": null,
            "description": null,
            "predicate": false,
            "modifier": false
        },
        {
            "index": 0,
            "isPredicate": true,
            "isModifier": false,
            "label": "109-1-1",
            "start": 1,
            "end": 1,
            "text": "is",
            "pb": null,
            "vn": null,
            "description": null,
            "predicate": true,
            "modifier": false
        },
        {
            "index": 0,
            "isPredicate": false,
            "isModifier": false,
            "label": null,
            "start": 2,
            "end": 2,
            "text": "The World .",
            "pb": null,
            "vn": null,
            "description": null,
            "predicate": false,
            "modifier": false
        }
    ],
    "props": [
        {
            "sense": "seem-109-1-1",
            "mainEvent": {
                "eventIndex": -1,
                "name": "E",
                "predicates": [
                    {
                        "eventName": "E",
                        "predicate": "Seem[EVENT(E = VnClassXml(verbNetId=seem-109-1-1)), Theme(A1[This]), Attribute(A2[The World])]",
                        "predicateType": "Seem",
                        "args": [
                            {
                                "type": "Theme",
                                "value": "This",
                                "eventIndex": -1
                            },
                            {
                                "type": "Attribute",
                                "value": "The World",
                                "eventIndex": -1
                            }
                        ],
                        "polarity": true,
                        "eventIndex": -1
                    }
                ]
            },
            "events": [],
            "spans": [
                {
                    "index": 0,
                    "isPredicate": false,
                    "isModifier": false,
                    "label": "A1 <-> Theme <-> topic",
                    "start": 0,
                    "end": 0,
                    "text": "This",
                    "pb": "A1",
                    "vn": "Theme",
                    "description": "topic",
                    "predicate": false,
                    "modifier": false
                },
                {
                    "index": 0,
                    "isPredicate": true,
                    "isModifier": false,
                    "label": "V <-> Verb",
                    "start": 1,
                    "end": 1,
                    "text": "is",
                    "pb": "V",
                    "vn": "Verb",
                    "description": "",
                    "predicate": true,
                    "modifier": false
                },
                {
                    "index": 0,
                    "isPredicate": false,
                    "isModifier": false,
                    "label": "A2 <-> Attribute <-> comment",
                    "start": 2,
                    "end": 3,
                    "text": "The World",
                    "pb": "A2",
                    "vn": "Attribute",
                    "description": "comment",
                    "predicate": false,
                    "modifier": false
                }
            ]
        }
    ]
}

